LICENSE
MANIFEST.in
README.md
setup.cfg
setup.py
dblue_stats/__init__.py
dblue_stats/config.py
dblue_stats/constants.py
dblue_stats/exceptions.py
dblue_stats/logger.py
dblue_stats/schema.py
dblue_stats/version.py
dblue_stats.egg-info/PKG-INFO
dblue_stats.egg-info/SOURCES.txt
dblue_stats.egg-info/dependency_links.txt
dblue_stats.egg-info/requires.txt
dblue_stats.egg-info/top_level.txt
dblue_stats/configs/logger.yaml
dblue_stats/configs/version.txt
dblue_stats/stats/__init__.py
dblue_stats/stats/tabular.py
requirements/requirements-base.txt
requirements/requirements-dev.txt
requirements/requirements.txt
tests/__init__.py